dmenu_hotkeys/__init__.py
dmenu_hotkeys/apps.py
dmenu_hotkeys/cli.py
dmenu_hotkeys/config.cfg
dmenu_hotkeys/config.py
dmenu_hotkeys/constants.py
dmenu_hotkeys/feeders.py
dmenu_hotkeys/parsers.py
dmenu_hotkeys/utils.py
dmenu_hotkeys-1.1.0.dist-info/AUTHORS.md
dmenu_hotkeys-1.1.0.dist-info/LICENSE
dmenu_hotkeys-1.1.0.dist-info/METADATA
dmenu_hotkeys-1.1.0.dist-info/WHEEL
dmenu_hotkeys-1.1.0.dist-info/entry_points.txt
dmenu_hotkeys-1.1.0.dist-info/top_level.txt
dmenu_hotkeys-1.1.0.dist-info/RECORD
