Metadata-Version: 2.1
Name: dmenu-hotkeys
Version: 1.1.0
Summary: Your hotkeys for various apps in 'dmenu' style.
Home-page: https://github.com/maledorak/dmenu_hotkeys
Author: Mariusz Korzekwa
Author-email: maledorak@gmail.com
License: MIT license
Keywords: dmenu_hotkeys
Platform: UNKNOWN
Classifier: Development Status :: 2 - Pre-Alpha
Classifier: Intended Audience :: Developers
Classifier: License :: OSI Approved :: MIT License
Classifier: Natural Language :: English
Classifier: Programming Language :: Python :: 2
Classifier: Programming Language :: Python :: 2.7
Classifier: Programming Language :: Python :: 3
Classifier: Programming Language :: Python :: 3.4
Classifier: Programming Language :: Python :: 3.5
Classifier: Programming Language :: Python :: 3.6
Classifier: Programming Language :: Python :: 3.7
Requires-Python: >=2.7,!=3.0.*,!=3.1.*,!=3.2.*,!=3.3.*
Requires-Dist: Click (>=7.0)
Requires-Dist: importlib-resources (>=1.0.0)
Requires-Dist: pathlib2
